StubLibrary/__init__.py
StubLibrary/commons.py
StubLibrary/endpoint.py
StubLibrary/http_stub.py
StubLibrary/robotlibcore.py
StubLibrary/statistic.py
robotframework_stublibrary-0.1.4.dist-info/DESCRIPTION.rst
robotframework_stublibrary-0.1.4.dist-info/METADATA
robotframework_stublibrary-0.1.4.dist-info/RECORD
robotframework_stublibrary-0.1.4.dist-info/WHEEL
robotframework_stublibrary-0.1.4.dist-info/metadata.json
robotframework_stublibrary-0.1.4.dist-info/top_level.txt
