Metadata-Version: 2.0
Name: robotframework-stublibrary
Version: 0.1.4
Summary: Stub utility library for Robot Framework
Home-page: https://github.com/ravihuang/Robotframework-StubLibrary
Author: Ravi Huang
Author-email: ravi.huang@gmail.com
License: Apache License 2.0
Keywords: robotframework testing testautomation Stub Http REST
Platform: any
Classifier: Development Status :: 2 - Pre-Alpha
Classifier: License :: OSI Approved :: Apache Software License
Classifier: Operating System :: OS Independent
Classifier: Programming Language :: Python
Classifier: Programming Language :: Python :: 2
Classifier: Programming Language :: Python :: 3
Classifier: Topic :: Software Development :: Testing
Classifier: Framework :: Robot Framework
Classifier: Framework :: Robot Framework :: Library
Requires-Dist: falcon
Requires-Dist: robotframework
Requires-Dist: psutil
Requires-Dist: webtest (>=2.0)
Requires-Dist: jsonpatch
Requires-Dist: falcon-multipart
Requires-Dist: jsonpointer
Requires-Dist: allpairspy
Requires-Dist: gevent
Requires-Dist: six
